MANIFEST.in
README.txt
setup.py
docs/HISTORY.txt
src/infrae/__init__.py
src/infrae.fileupload.egg-info/PKG-INFO
src/infrae.fileupload.egg-info/SOURCES.txt
src/infrae.fileupload.egg-info/dependency_links.txt
src/infrae.fileupload.egg-info/entry_points.txt
src/infrae.fileupload.egg-info/namespace_packages.txt
src/infrae.fileupload.egg-info/not-zip-safe
src/infrae.fileupload.egg-info/requires.txt
src/infrae.fileupload.egg-info/top_level.txt
src/infrae/fileupload/__init__.py
src/infrae/fileupload/middleware.py
src/infrae/fileupload/standalone.py