Metadata-Version: 1.0
Name: infrae.fileupload
Version: 1.0
Summary: WSGI middleware to manage upload of files
Home-page: http://infrae.com/products/silva
Author: Infrae
Author-email: info@infrae.com
License: BSD
Keywords: silva cms file upload zope
Platform: UNKNOWN
Classifier: License :: OSI Approved :: BSD License
Classifier: Programming Language :: Python
Classifier: Topic :: Software Development :: Libraries :: Python Modules
